LICENSE
MANIFEST.in
README.rst
pyproject.toml
setup.cfg
setup.py
django_taskq/__init__.py
django_taskq/admin.py
django_taskq/apps.py
django_taskq/celery.py
django_taskq/celery.pyi
django_taskq/models.py
django_taskq/tests.py
django_taskq.egg-info/PKG-INFO
django_taskq.egg-info/SOURCES.txt
django_taskq.egg-info/dependency_links.txt
django_taskq.egg-info/requires.txt
django_taskq.egg-info/top_level.txt
django_taskq/management/__init__.py
django_taskq/management/commands/__init__.py
django_taskq/management/commands/taskq.py
django_taskq/migrations/0001_initial.py
django_taskq/migrations/0002_remove_task_repr.py
django_taskq/migrations/0003_tasksummary.py
django_taskq/migrations/__init__.py
django_taskq/templates/admin/task_summary_change_list.html